Metadata-Version: 2.4
Name: llama-index-vector-stores-awsdocdb
Version: 0.4.0
Summary: llama-index vector_stores awsdocdb integration
Author: Vidur Modgil, vmod2005@gmail.com
Author-email: Prajwal Saokar <prajwal.saokar@gmail.com>
License-Expression: MIT
License-File: LICENSE
Requires-Python: <4.0,>=3.9
Requires-Dist: llama-index-core<0.14,>=0.13.0
Requires-Dist: pymongo<5,>=4.6.1
